MANIFEST.in
setup.py
veta_python_novaclient_ext/__init__.py
veta_python_novaclient_ext.egg-info/PKG-INFO
veta_python_novaclient_ext.egg-info/SOURCES.txt
veta_python_novaclient_ext.egg-info/dependency_links.txt
veta_python_novaclient_ext.egg-info/requires.txt
veta_python_novaclient_ext.egg-info/top_level.txt