Metadata-Version: 1.0
Name: veta-python-novaclient-ext
Version: 1.0.0
Summary: Veta Backup extension for OS novaclient.
Home-page: http://www.gridcentric.com/
Author: Gridcentric
Author-email: support@gridcentric.com
License: UNKNOWN
Platform: UNKNOWN
Classifier: Development Status :: 5 - Production/Stable
Classifier: Environment :: Console
Classifier: Environment :: OpenStack
Classifier: Intended Audience :: Developers
Classifier: Intended Audience :: Information Technology
Classifier: License :: OSI Approved :: Apache Software License
Classifier: Operating System :: OS Independent
Classifier: Programming Language :: Python
